mindrove_gesture/__init__.py
mindrove_gesture/fine_tune.py
mindrove_gesture/inference.py
mindrove_gesture/record.py
mindrove_gesture/utils.py
mindrove_gesture-0.1.10.dist-info/METADATA
mindrove_gesture-0.1.10.dist-info/WHEEL
mindrove_gesture-0.1.10.dist-info/entry_points.txt
mindrove_gesture-0.1.10.dist-info/top_level.txt
mindrove_gesture-0.1.10.dist-info/RECORD
