Metadata-Version: 2.1
Name: mindrove-gesture
Version: 0.1.10
Summary: A package for recording and analyzing gestures with MindRove.
Home-page: https://github.com/budzs/mindrove_gesture
Author: MindRove
Author-email: zsofia.budai@mindrove.com
License: UNKNOWN
Platform: UNKNOWN
Classifier: Programming Language :: Python :: 3
Classifier: License :: OSI Approved :: MIT License
Classifier: Operating System :: OS Independent
Requires-Python: >=3.7, <3.11
Requires-Dist: numpy
Requires-Dist: opencv-python
Requires-Dist: scikit-learn
Requires-Dist: tensorflow==2.12.0
Requires-Dist: mindrove
Requires-Dist: keyboard
